qubitclient/__init__.py
qubitclient/draw/__init__.py
qubitclient/draw/optpipulsepltplotter.py
qubitclient/draw/optpipulseplyplotter.py
qubitclient/draw/pltmanager.py
qubitclient/draw/pltplotter.py
qubitclient/draw/plymanager.py
qubitclient/draw/plyplotter.py
qubitclient/draw/powershiftnnscopepltplotter.py
qubitclient/draw/powershiftnnscopeplyplotter.py
qubitclient/draw/powershiftpltplotter.py
qubitclient/draw/powershiftplyplotter.py
qubitclient/draw/rabicospltplotter.py
qubitclient/draw/rabicosplyplotter.py
qubitclient/draw/ramseypltplotter.py
qubitclient/draw/ramseyplyplotter.py
qubitclient/draw/s21peakpltplotter.py
qubitclient/draw/s21peakplyplotter.py
qubitclient/draw/s21vfluxnnscopepltplotter.py
qubitclient/draw/s21vfluxnnscopeplyplotter.py
qubitclient/draw/s21vfluxscopepltplotter.py
qubitclient/draw/s21vfluxscopeplyplotter.py
qubitclient/draw/singleshotpltplotter.py
qubitclient/draw/singleshotplyplotter.py
qubitclient/draw/spectrum2dnnscopepltplotter.py
qubitclient/draw/spectrum2dnnscopeplyplotter.py
qubitclient/draw/spectrum2dscopepltplotter.py
qubitclient/draw/spectrum2dscopeplyplotter.py
qubitclient/draw/spectrumnnscopepltplotter.py
qubitclient/draw/spectrumnnscopeplyplotter.py
qubitclient/draw/spectrumpltplotter.py
qubitclient/draw/spectrumplyplotter.py
qubitclient/draw/t1fitpltplotter.py
qubitclient/draw/t1fitplyplotter.py
qubitclient/draw/t2fitpltplotter.py
qubitclient/draw/t2fitplyplotter.py
qubitclient/nnscope/nnscope.py
qubitclient/nnscope/postprocess.py
qubitclient/nnscope/task.py
qubitclient/nnscope/nnscope_api/curve/__init__.py
qubitclient/nnscope/nnscope_api/curve/curve_type.py
qubitclient/nnscope/utils/data_convert.py
qubitclient/nnscope/utils/data_parser.py
qubitclient/nnscope/utils/request_tool.py
qubitclient/nnscope/utils/result_parser.py
qubitclient/scope/postprocess.py
qubitclient/scope/scope.py
qubitclient/scope/task.py
qubitclient/scope/scope_api/__init__.py
qubitclient/scope/scope_api/client.py
qubitclient/scope/scope_api/errors.py
qubitclient-0.2.6.dist-info/licenses/LICENSE
qubitclient-0.2.6.dist-info/METADATA
qubitclient-0.2.6.dist-info/WHEEL
qubitclient-0.2.6.dist-info/top_level.txt
qubitclient-0.2.6.dist-info/zip-safe
qubitclient-0.2.6.dist-info/RECORD
