Metadata-Version: 2.4
Name: qubitclient
Version: 0.2.6
Summary: qubit analysis client
Home-page: https://github.com/yaqiangsun/QubitClient
Author: Yaqiang Sun
Author-email: Yaqiang Sun <sunyaking@163.com>
License: GPL-3.0
Requires-Python: >=3.8
License-File: LICENSE
Requires-Dist: attrs>=25.4.0
Requires-Dist: httpx>=0.28.1
Requires-Dist: numpy>=1.26.4
Requires-Dist: requests>=2.32.5
Provides-Extra: full
Requires-Dist: matplotlib>=3.9; extra == "full"
Requires-Dist: opencv-python>=4.12; extra == "full"
Requires-Dist: opencv-python-headless>=4.12; extra == "full"
Requires-Dist: plotly>=6.4.0; extra == "full"
Requires-Dist: scipy>=1.10; extra == "full"
Dynamic: author
Dynamic: home-page
Dynamic: license-file
Dynamic: requires-python
